ReadMe.md
ReadMe_pypi.md
setup.py
pericaat/API.py
pericaat/Scwrl.py
pericaat/__init__.py
pericaat/inputParser.py
pericaat/intercaatInterface.py
pericaat/main.py
pericaat/mutate_model.py
pericaat/pdb_fixinsert.py
pericaat/simple_mutate.py
pericaat.egg-info/PKG-INFO
pericaat.egg-info/SOURCES.txt
pericaat.egg-info/dependency_links.txt
pericaat.egg-info/entry_points.txt
pericaat.egg-info/requires.txt
pericaat.egg-info/top_level.txt