Metadata-Version: 2.1
Name: pericaat
Version: 0.9
Summary: The Interface Extension program was developed to identify pharmacologically relevant residues at the periphery of a protein’s interface from a known three-dimensional structure
Home-page: https://github.com/eved1018/InterfaceExtension
Author: Evan Edelstein
Author-email: edelsteinevan@gmail.com
License: MIT
Platform: UNKNOWN
